gh_notify.py
gh_notify-0.0.2.dist-info/METADATA
gh_notify-0.0.2.dist-info/WHEEL
gh_notify-0.0.2.dist-info/entry_points.txt
gh_notify-0.0.2.dist-info/RECORD
